jafkafe/__init__.py
jafkafe/simulator.py
freeds_lab_jaffle_kafe-0.1.3.dist-info/LICENSE
freeds_lab_jaffle_kafe-0.1.3.dist-info/METADATA
freeds_lab_jaffle_kafe-0.1.3.dist-info/WHEEL
freeds_lab_jaffle_kafe-0.1.3.dist-info/RECORD
