Metadata-Version: 2.3
Name: freeds-lab-jaffle-kafe
Version: 0.1.3
Summary: 
License: GNU v 3
Author: freeds@jensbox.se
Requires-Python: >=3.11, <4.0
Classifier: License :: Other/Proprietary License
Classifier: Programming Language :: Python :: 3
Classifier: Programming Language :: Python :: 3.11
Classifier: Programming Language :: Python :: 3.12
Classifier: Programming Language :: Python :: 3.13
Requires-Dist: jafkafegen (>0.4.16)
Requires-Dist: loguru (>=0.7.3,<0.8.0)
